clientpkgs/AccountsClient.py
clientpkgs/ClustersClient.py
clientpkgs/DBSqlClient.py
clientpkgs/DbfsClient.py
clientpkgs/IPAccessClient.py
clientpkgs/InitScriptsClient.py
clientpkgs/JobRunsClient.py
clientpkgs/JobsClient.py
clientpkgs/LibrariesClient.py
clientpkgs/MLFlowClient.py
clientpkgs/PoliciesClient.py
clientpkgs/PoolsClient.py
clientpkgs/ReposClient.py
clientpkgs/ScimClient.py
clientpkgs/SecretsClient.py
clientpkgs/TableACLsClient.py
clientpkgs/TokensClient.py
clientpkgs/WSSettingsClient.py
clientpkgs/WorkspaceClient.py
clientpkgs/__init__.py
core/__init__.py
core/dbclient.py
core/logging_utils.py
core/parser.py
core/wmconstants.py
dbr_profiler_tool-0.4.2.dist-info/METADATA
dbr_profiler_tool-0.4.2.dist-info/NOTICE
dbr_profiler_tool-0.4.2.dist-info/WHEEL
dbr_profiler_tool-0.4.2.dist-info/top_level.txt
dbr_profiler_tool-0.4.2.dist-info/RECORD
