Metadata-Version: 2.1
Name: dbr-profiler-tool
Version: 0.4.2
Summary: Databricks Profiling Tool
Home-page: https://github.com/databrickslabs/yoohoo
Author: RKMurali
Author-email: ramdas.murali@databricks.com
License: https://github.com/databrickslabs/profile/blob/master/LICENSE
Classifier: Programming Language :: Python :: 3
Classifier: Operating System :: OS Independent
Requires-Python: >=3.6
License-File: NOTICE
Requires-Dist: requests
